jesth/__init__.py
jesth/__main__.py
jesth/box/__init__.py
jesth/const/__init__.py
jesth/converter/__init__.py
jesth/dataformat/__init__.py
jesth/dataformat/binary.py
jesth/dataformat/text.py
jesth/deserializer/__init__.py
jesth/document/__init__.py
jesth/error/__init__.py
jesth/errors/__init__.py
jesth/misc/__init__.py
jesth/parser/.private
jesth/parser/__init__.py
jesth/renderer/.private
jesth/renderer/__init__.py
jesth/section/__init__.py
jesth/serializer/__init__.py
jesth/tagbyte/__init__.py
jesth/util/.private
jesth/util/__init__.py
jesth/validator/__init__.py
tests/__init__.py
tests/test_box.py
tests/test_converter.py
tests/test_document.py
tests/test_misc.py
tests/test_parser.py
tests/test_renderer.py
tests/test_root_imports.py
tests/test_section.py
tests/test_validator.py
jesth-0.0.10.dist-info/LICENSE
jesth-0.0.10.dist-info/METADATA
jesth-0.0.10.dist-info/WHEEL
jesth-0.0.10.dist-info/entry_points.txt
jesth-0.0.10.dist-info/top_level.txt
jesth-0.0.10.dist-info/RECORD
