Metadata-Version: 2.1
Name: jesth
Version: 0.0.10
Summary: Human-readable versatile data format
Home-page: https://github.com/pyrustic/jesth
Author: Pyrustic Evangelist
Author-email: rusticalex@yahoo.com
Maintainer: Pyrustic Evangelist
Maintainer-email: rusticalex@yahoo.com
License: MIT
Keywords: serialization,library,format,collections,data,markup,parser,config,configuration,renderer,language,typed,data-structure,pyrustic
Platform: UNKNOWN
Classifier: Programming Language :: Python :: 3
Classifier: License :: OSI Approved :: MIT License
Classifier: Operating System :: OS Independent
Requires-Python: >=3.5
License-File: LICENSE
